sysame/__init__.py
sysame/py.typed
sysame/cube/__init__.py
sysame/cube/cube.py
sysame/cube/spg2cube.py
sysame/data_sources/nts.py
sysame/matrix/__init__.py
sysame/matrix/mx.py
sysame/matsim/__init__.py
sysame/matsim/matsim_network.py
sysame/matsim/parse_plans.py
sysame/matsim/plan_parser.py
sysame/plotting/__init__.py
sysame/plotting/plotting.py
sysame/saturn/__init__.py
sysame/saturn/saturn.py
sysame/utils/__init__.py
sysame/utils/acceleration.py
sysame/utils/cpu_utils.py
sysame/utils/gpu_utils.py
sysame/utils/npu_utils.py
sysame/utils/space_utils.py
sysame-0.0.17.dist-info/METADATA
sysame-0.0.17.dist-info/WHEEL
sysame-0.0.17.dist-info/licenses/LICENSE.md
sysame-0.0.17.dist-info/RECORD
