Metadata-Version: 2.4
Name: sysame
Version: 0.0.17
Summary: Transport Modelling Helper Package
Author-email: "M.I." <help@sysame.com>
License-File: LICENSE.md
Requires-Python: >=3.12
Requires-Dist: contextily>=1.6.2
Requires-Dist: dbfread>=2.0.7
Requires-Dist: lxml>=6.0.2
Requires-Dist: matplotlib>=3.10.3
Requires-Dist: mypy>=1.15.0
Requires-Dist: networkx>=3.4.2
Requires-Dist: numpy>=2.2.5
Requires-Dist: openmatrix>=0.3.5.0
Requires-Dist: pandas>=2.2.3
Requires-Dist: polars>=1.29.0
Requires-Dist: py7zr>=0.22.0
Requires-Dist: pyarrow>=20.0.0
Requires-Dist: pytest>=8.3.5
Requires-Dist: scipy>=1.15.3
Requires-Dist: seaborn>=0.13.2
Requires-Dist: shapely>=2.1.0
